odoo10_addon_medical_insurance-10.0.1.0.0.99.dev11-py2.7-nspkg.pth
odoo/addons/medical_insurance/README.rst
odoo/addons/medical_insurance/__init__.py
odoo/addons/medical_insurance/__manifest__.py
odoo/addons/medical_insurance/demo/medical_insurance_company_demo.xml
odoo/addons/medical_insurance/demo/medical_insurance_plan_demo.xml
odoo/addons/medical_insurance/demo/medical_insurance_template_demo.xml
odoo/addons/medical_insurance/demo/product_product_demo.xml
odoo/addons/medical_insurance/i18n/es.po
odoo/addons/medical_insurance/i18n/es_AR.po
odoo/addons/medical_insurance/i18n/es_CO.po
odoo/addons/medical_insurance/i18n/fr.po
odoo/addons/medical_insurance/i18n/medical_insurance.pot
odoo/addons/medical_insurance/i18n/nl_NL.po
odoo/addons/medical_insurance/i18n/pt_BR.po
odoo/addons/medical_insurance/i18n/ro.po
odoo/addons/medical_insurance/models/__init__.py
odoo/addons/medical_insurance/models/medical_insurance_company.py
odoo/addons/medical_insurance/models/medical_insurance_plan.py
odoo/addons/medical_insurance/models/medical_insurance_template.py
odoo/addons/medical_insurance/models/medical_patient.py
odoo/addons/medical_insurance/models/product_product.py
odoo/addons/medical_insurance/models/res_partner.py
odoo/addons/medical_insurance/security/ir.model.access.csv
odoo/addons/medical_insurance/static/description/icon.png
odoo/addons/medical_insurance/tests/__init__.py
odoo/addons/medical_insurance/tests/test_medical_insurance_company.py
odoo/addons/medical_insurance/views/medical_insurance_company_view.xml
odoo/addons/medical_insurance/views/medical_insurance_plan_view.xml
odoo/addons/medical_insurance/views/medical_insurance_template_view.xml
odoo/addons/medical_insurance/views/medical_menu.xml
odoo/addons/medical_insurance/views/medical_patient_view.xml
odoo10_addon_medical_insurance-10.0.1.0.0.99.dev11.dist-info/METADATA
odoo10_addon_medical_insurance-10.0.1.0.0.99.dev11.dist-info/RECORD
odoo10_addon_medical_insurance-10.0.1.0.0.99.dev11.dist-info/WHEEL
odoo10_addon_medical_insurance-10.0.1.0.0.99.dev11.dist-info/namespace_packages.txt
odoo10_addon_medical_insurance-10.0.1.0.0.99.dev11.dist-info/top_level.txt
