Metadata-Version: 2.1
Name: odoo10-addon-medical-insurance
Version: 10.0.1.0.0.99.dev11
Summary: Medical Insurance
Home-page: https://laslabs.com
Author: LasLabs, Odoo Community Association (OCA)
Author-email: support@odoo-community.org
License: GPL-3
Platform: UNKNOWN
Classifier: Programming Language :: Python
Classifier: Framework :: Odoo
Classifier: License :: OSI Approved :: GNU General Public License v3 (GPLv3)
Requires-Python: ~=2.7
Requires-Dist: odoo10-addon-medical
Requires-Dist: odoo (<10.1dev,>=10.0)
